CHANGELOG.md
LICENSE
README.md
edmunds-instance
requirements.txt
setup.cfg
setup.config.ini
setup.py
config/app.py
docs/changes.md
docs/index.md
docs/mkdocs.yml
docs/auth/basic.md
docs/auth/introduction.md
docs/auth/roles.md
docs/auth/session.md
docs/auth/token.md
docs/coreconcepts/applicationmiddleware.md
docs/coreconcepts/serviceproviders.md
docs/data/caching.md
docs/data/database.md
docs/data/migrations.md
docs/data/orm.md
docs/data/storage.md
docs/gettingstarted/afreshstart.md
docs/gettingstarted/configuration.md
docs/gettingstarted/console.md
docs/gettingstarted/debuggingandprofiling.md
docs/gettingstarted/logginganderrors.md
docs/gettingstarted/testing.md
docs/http/inputandvalidation.md
docs/http/request.md
docs/http/requestmiddleware.md
docs/http/response.md
docs/http/routing.md
docs/http/session.md
docs/http/visitor.md
docs/localization/formatting.md
docs/localization/introduction.md
docs/localization/location.md
docs/localization/translations.md
edmunds/__init__.py
edmunds/application.py
edmunds/globals.py
edmunds/auth/__init__.py
edmunds/auth/authmanager.py
edmunds/auth/middleware/__init__.py
edmunds/auth/middleware/basicauthmiddleware.py
edmunds/auth/middleware/rolesacceptedmiddleware.py
edmunds/auth/middleware/rolesrequiredmiddleware.py
edmunds/auth/middleware/sessionauthmiddleware.py
edmunds/auth/middleware/tokenauthmiddleware.py
edmunds/auth/models/__init__.py
edmunds/auth/models/rolemixin.py
edmunds/auth/models/usermixin.py
edmunds/auth/providers/__init__.py
edmunds/auth/providers/authserviceprovider.py
edmunds/cache/__init__.py
edmunds/cache/cachemanager.py
edmunds/cache/drivers/__init__.py
edmunds/cache/drivers/file.py
edmunds/cache/drivers/memcached.py
edmunds/cache/drivers/redis.py
edmunds/cache/providers/__init__.py
edmunds/cache/providers/cacheserviceprovider.py
edmunds/config/__init__.py
edmunds/config/config.py
edmunds/console/__init__.py
edmunds/console/command.py
edmunds/console/manager.py
edmunds/database/__init__.py
edmunds_framework.egg-info/PKG-INFO
edmunds_framework.egg-info/SOURCES.txt
edmunds_framework.egg-info/dependency_links.txt
edmunds_framework.egg-info/requires.txt
edmunds_framework.egg-info/top_level.txt
